README.md
setup.py
atank/__init__.py
atank/main.py
atank.egg-info/PKG-INFO
atank.egg-info/SOURCES.txt
atank.egg-info/dependency_links.txt
atank.egg-info/top_level.txt