Metadata-Version: 2.1
Name: atank
Version: 1.0
Summary: <项目的简单描述>
Home-page: https://gitee.com/shwdbd/atank
Author: shwangjj
Author-email: shwangjj@163.com
Maintainer: shwangjj
Maintainer-email: shwanjj@163.com
License: BSD License
Platform: all
Classifier: Programming Language :: Python :: 3.6
Classifier: Programming Language :: Python :: 3.7
Classifier: Programming Language :: Python :: 3.8
Classifier: License :: OSI Approved :: MIT License
Classifier: Operating System :: OS Independent
Requires-Python: >=3.6
